unc_tools/__init__.py
unc_tools/default_functions.py
unc_tools/exceptions.py
unc_tools/patches.py
unc_tools/py.typed
unc_tools/unc_regression.py
uncertainty_tools-0.0.1.dist-info/METADATA
uncertainty_tools-0.0.1.dist-info/WHEEL
uncertainty_tools-0.0.1.dist-info/licenses/LICENSE
uncertainty_tools-0.0.1.dist-info/RECORD
