Metadata-Version: 2.4
Name: uncertainty_tools
Version: 0.0.1
Summary: Utilities for uncertainty-aware regression and symbolic function helpers.
Author-email: Savateykin Yaroslav <yaroslavsavateikinwork@yandex.ru>
License: MIT License
License-File: LICENSE
Classifier: Intended Audience :: Science/Research
Classifier: License :: OSI Approved :: MIT License
Classifier: Programming Language :: Python :: 3
Classifier: Programming Language :: Python :: 3.10
Classifier: Programming Language :: Python :: 3.11
Classifier: Programming Language :: Python :: 3.12
Classifier: Topic :: Scientific/Engineering :: Mathematics
Classifier: Typing :: Typed
Requires-Python: >=3.10
Requires-Dist: matplotlib>=3.7
Requires-Dist: numpy>=1.23
Requires-Dist: pandas>=1.5
Requires-Dist: scipy>=1.10
Requires-Dist: sympy>=1.11
Requires-Dist: uncertainties>=3.1
Provides-Extra: test
Requires-Dist: pytest>=7.0; extra == 'test'
